ecs_auditor
