Metadata-Version: 1.1
Name: ecs-auditor
Version: 1.0.7
Summary: An ECS Auditor
Home-page: https://github.com/SpekoTechnologies/ecs-auditor
Author: Speko Technologies
Author-email: info@speko.io
License: UNKNOWN
Keywords: ecs auditor aws ssm python
Platform: UNKNOWN
Classifier: Development Status :: 3 - Alpha
Classifier: Intended Audience :: Developers
Classifier: Topic :: Software Development :: Build Tools
Classifier: License :: OSI Approved :: MIT License
Classifier: Programming Language :: Python :: 2
Classifier: Programming Language :: Python :: 2.7
